{
  "status": "success",
  "data": {
    "resultType": "matrix",
    "result": [
      {
        "metric": {
          "host_id": "343177628"
        },
        "values": [
          [
            1678090023,
            "183934976"
          ],
          [
            1678090143,
            "239099904"
          ],
          [
            1678090263,
            "199258112"
          ],
          [
            1678090383,
            "214380544"
          ],
          [
            1678090503,
            "241438720"
          ],
          [
            1678090623,
            "216625152"
          ],
          [
            1678090743,
            "236769280"
          ],
          [
            1678090863,
            "240304128"
          ],
          [
            1678090983,
            "198684672"
          ],
          [
            1678091103,
            "236265472"
          ],
          [
            1678091223,
            "234295296"
          ],
          [
            1678091343,
            "210640896"
          ],
          [
            1678091463,
            "315174912"
          ],
          [
            1678091583,
            "318582784"
          ],
          [
            1678091703,
            "289464320"
          ],
          [
            1678091823,
            "325173248"
          ],
          [
            1678091943,
            "235880448"
          ],
          [
            1678092063,
            "188485632"
          ],
          [
            1678092183,
            "223346688"
          ],
          [
            1678092303,
            "219365376"
          ],
          [
            1678092423,
            "214081536"
          ],
          [
            1678092543,
            "238616576"
          ],
          [
            1678092663,
            "183549952"
          ],
          [
            1678092783,
            "232534016"
          ],
          [
            1678092903,
            "241311744"
          ],
          [
            1678093023,
            "208654336"
          ],
          [
            1678093143,
            "245923840"
          ],
          [
            1678093263,
            "245002240"
          ],
          [
            1678093383,
            "193794048"
          ],
          [
            1678093503,
            "250368000"
          ],
          [
            1678093623,
            "239759360"
          ],
          [
            1678093743,
            "202416128"
          ],
          [
            1678093863,
            "229810176"
          ],
          [
            1678093983,
            "241598464"
          ],
          [
            1678094103,
            "193622016"
          ],
          [
            1678094223,
            "236187648"
          ],
          [
            1678094343,
            "216596480"
          ],
          [
            1678094463,
            "183607296"
          ],
          [
            1678094583,
            "240033792"
          ],
          [
            1678094703,
            "237928448"
          ],
          [
            1678094823,
            "192765952"
          ],
          [
            1678094943,
            "231088128"
          ],
          [
            1678095063,
            "2703167488"
          ],
          [
            1678095183,
            "2693742592"
          ],
          [
            1678095303,
            "2644901888"
          ],
          [
            1678095423,
            "2678665216"
          ],
          [
            1678095543,
            "2676281344"
          ],
          [
            1678095663,
            "2637529088"
          ],
          [
            1678095783,
            "2675757056"
          ],
          [
            1678095903,
            "2674216960"
          ],
          [
            1678096023,
            "2646388736"
          ],
          [
            1678096143,
            "2669449216"
          ],
          [
            1678096263,
            "2634444800"
          ],
          [
            1678096383,
            "2673582080"
          ],
          [
            1678096503,
            "2676531200"
          ],
          [
            1678096623,
            "2641391616"
          ],
          [
            1678096743,
            "2582736896"
          ],
          [
            1678096863,
            "2624200704"
          ],
          [
            1678096983,
            "2620399616"
          ],
          [
            1678097103,
            "176754688"
          ],
          [
            1678097223,
            "249942016"
          ],
          [
            1678097343,
            "229535744"
          ],
          [
            1678097463,
            "196747264"
          ],
          [
            1678097583,
            "233762816"
          ],
          [
            1678097703,
            "247349248"
          ],
          [
            1678097823,
            "199852032"
          ],
          [
            1678097943,
            "246579200"
          ],
          [
            1678098063,
            "233385984"
          ],
          [
            1678098183,
            "200527872"
          ],
          [
            1678098303,
            "243576832"
          ],
          [
            1678098423,
            "248352768"
          ],
          [
            1678098543,
            "199122944"
          ],
          [
            1678098663,
            "252260352"
          ],
          [
            1678098783,
            "259051520"
          ],
          [
            1678098903,
            "211169280"
          ],
          [
            1678099023,
            "198103040"
          ],
          [
            1678099143,
            "204992512"
          ],
          [
            1678099263,
            "201146368"
          ],
          [
            1678099383,
            "200777728"
          ],
          [
            1678099503,
            "187174912"
          ],
          [
            1678099623,
            "258895872"
          ],
          [
            1678099743,
            "249262080"
          ],
          [
            1678099863,
            "204816384"
          ],
          [
            1678099983,
            "231256064"
          ],
          [
            1678100103,
            "240300032"
          ],
          [
            1678100223,
            "226099200"
          ],
          [
            1678100343,
            "240545792"
          ],
          [
            1678100463,
            "198811648"
          ],
          [
            1678100583,
            "217112576"
          ],
          [
            1678100703,
            "218046464"
          ],
          [
            1678100823,
            "212172800"
          ],
          [
            1678100943,
            "207446016"
          ],
          [
            1678101063,
            "197931008"
          ],
          [
            1678101183,
            "249225216"
          ],
          [
            1678101303,
            "228257792"
          ],
          [
            1678101423,
            "197111808"
          ],
          [
            1678101543,
            "241172480"
          ],
          [
            1678101663,
            "238067712"
          ],
          [
            1678101783,
            "191254528"
          ],
          [
            1678101903,
            "239063040"
          ],
          [
            1678102023,
            "231251968"
          ],
          [
            1678102143,
            "184344576"
          ],
          [
            1678102263,
            "248250368"
          ],
          [
            1678102383,
            "254971904"
          ],
          [
            1678102503,
            "191475712"
          ],
          [
            1678102623,
            "257032192"
          ],
          [
            1678102743,
            "274006016"
          ],
          [
            1678102863,
            "221097984"
          ],
          [
            1678102983,
            "267919360"
          ],
          [
            1678103103,
            "253386752"
          ],
          [
            1678103223,
            "193884160"
          ],
          [
            1678103343,
            "265117696"
          ],
          [
            1678103463,
            "255504384"
          ],
          [
            1678103583,
            "215523328"
          ],
          [
            1678103703,
            "253718528"
          ],
          [
            1678103823,
            "264278016"
          ],
          [
            1678103943,
            "201773056"
          ],
          [
            1678104063,
            "256856064"
          ],
          [
            1678104183,
            "258953216"
          ],
          [
            1678104303,
            "224722944"
          ],
          [
            1678104423,
            "251424768"
          ],
          [
            1678104543,
            "257572864"
          ],
          [
            1678104663,
            "257179648"
          ],
          [
            1678104783,
            "243257344"
          ],
          [
            1678104903,
            "205205504"
          ],
          [
            1678105023,
            "259059712"
          ],
          [
            1678105143,
            "241238016"
          ],
          [
            1678105263,
            "203501568"
          ],
          [
            1678105383,
            "242454528"
          ],
          [
            1678105503,
            "261308416"
          ],
          [
            1678105623,
            "208052224"
          ],
          [
            1678105743,
            "229576704"
          ],
          [
            1678105863,
            "221347840"
          ],
          [
            1678105983,
            "188485632"
          ],
          [
            1678106103,
            "227618816"
          ],
          [
            1678106223,
            "253571072"
          ],
          [
            1678106343,
            "200392704"
          ],
          [
            1678106463,
            "242114560"
          ],
          [
            1678106583,
            "240029696"
          ],
          [
            1678106703,
            "205029376"
          ],
          [
            1678106823,
            "245235712"
          ],
          [
            1678106943,
            "232202240"
          ],
          [
            1678107063,
            "197038080"
          ],
          [
            1678107183,
            "244572160"
          ],
          [
            1678107303,
            "233574400"
          ],
          [
            1678107423,
            "210026496"
          ],
          [
            1678107543,
            "249573376"
          ],
          [
            1678107663,
            "241856512"
          ],
          [
            1678107783,
            "223567872"
          ],
          [
            1678107903,
            "255627264"
          ],
          [
            1678108023,
            "224448512"
          ],
          [
            1678108143,
            "216236032"
          ],
          [
            1678108263,
            "241999872"
          ],
          [
            1678108383,
            "207556608"
          ],
          [
            1678108503,
            "269942784"
          ],
          [
            1678108623,
            "259346432"
          ],
          [
            1678108743,
            "202145792"
          ],
          [
            1678108863,
            "265973760"
          ],
          [
            1678108983,
            "247070720"
          ],
          [
            1678109103,
            "212189184"
          ],
          [
            1678109223,
            "242950144"
          ],
          [
            1678109343,
            "267165696"
          ],
          [
            1678109463,
            "192487424"
          ],
          [
            1678109583,
            "283721728"
          ],
          [
            1678109703,
            "283111424"
          ],
          [
            1678109823,
            "246046720"
          ],
          [
            1678109943,
            "284557312"
          ],
          [
            1678110063,
            "307650560"
          ],
          [
            1678110183,
            "230354944"
          ],
          [
            1678110303,
            "242552832"
          ],
          [
            1678110423,
            "235577344"
          ],
          [
            1678110543,
            "177217536"
          ],
          [
            1678110663,
            "238579712"
          ],
          [
            1678110783,
            "262955008"
          ],
          [
            1678110903,
            "220905472"
          ],
          [
            1678111023,
            "242180096"
          ],
          [
            1678111143,
            "249470976"
          ],
          [
            1678111263,
            "204193792"
          ],
          [
            1678111383,
            "235737088"
          ],
          [
            1678111503,
            "227766272"
          ],
          [
            1678111623,
            "211480576"
          ],
          [
            1678111743,
            "260804608"
          ],
          [
            1678111863,
            "252059648"
          ],
          [
            1678111983,
            "259059712"
          ],
          [
            1678112103,
            "246099968"
          ],
          [
            1678112223,
            "177795072"
          ],
          [
            1678112343,
            "251768832"
          ],
          [
            1678112463,
            "243826688"
          ],
          [
            1678112583,
            "188747776"
          ],
          [
            1678112703,
            "261181440"
          ],
          [
            1678112823,
            "226193408"
          ],
          [
            1678112943,
            "193495040"
          ],
          [
            1678113063,
            "251445248"
          ],
          [
            1678113183,
            "234319872"
          ],
          [
            1678113303,
            "198758400"
          ],
          [
            1678113423,
            "205086720"
          ],
          [
            1678113543,
            "207618048"
          ],
          [
            1678113663,
            "289345536"
          ],
          [
            1678113783,
            "295563264"
          ],
          [
            1678113903,
            "248004608"
          ],
          [
            1678114023,
            "288940032"
          ],
          [
            1678114143,
            "285495296"
          ],
          [
            1678114263,
            "273571840"
          ],
          [
            1678114383,
            "299544576"
          ],
          [
            1678114503,
            "298930176"
          ],
          [
            1678114623,
            "282005504"
          ],
          [
            1678114743,
            "304168960"
          ],
          [
            1678114863,
            "253898752"
          ],
          [
            1678114983,
            "235782144"
          ],
          [
            1678115103,
            "254038016"
          ],
          [
            1678115223,
            "277118976"
          ],
          [
            1678115343,
            "239489024"
          ],
          [
            1678115463,
            "285888512"
          ],
          [
            1678115583,
            "257941504"
          ],
          [
            1678115703,
            "239284224"
          ],
          [
            1678115823,
            "258572288"
          ],
          [
            1678115943,
            "253652992"
          ],
          [
            1678116063,
            "248242176"
          ],
          [
            1678116183,
            "266207232"
          ],
          [
            1678116303,
            "227012608"
          ],
          [
            1678116423,
            "261644288"
          ],
          [
            1678116543,
            "257798144"
          ],
          [
            1678116663,
            "215863296"
          ],
          [
            1678116783,
            "259993600"
          ],
          [
            1678116903,
            "269905920"
          ],
          [
            1678117023,
            "220397568"
          ],
          [
            1678117143,
            "245170176"
          ],
          [
            1678117263,
            "243720192"
          ],
          [
            1678117383,
            "195854336"
          ],
          [
            1678117503,
            "261267456"
          ],
          [
            1678117623,
            "236036096"
          ],
          [
            1678117743,
            "224387072"
          ],
          [
            1678117863,
            "274391040"
          ],
          [
            1678117983,
            "269746176"
          ],
          [
            1678118103,
            "232099840"
          ],
          [
            1678118223,
            "226586624"
          ],
          [
            1678118343,
            "210563072"
          ],
          [
            1678118463,
            "193208320"
          ],
          [
            1678118583,
            "218279936"
          ],
          [
            1678118703,
            "222838784"
          ],
          [
            1678118823,
            "196022272"
          ],
          [
            1678118943,
            "192753664"
          ],
          [
            1678119063,
            "226160640"
          ],
          [
            1678119183,
            "225824768"
          ],
          [
            1678119303,
            "228487168"
          ],
          [
            1678119423,
            "192471040"
          ],
          [
            1678119543,
            "184815616"
          ],
          [
            1678119663,
            "248778752"
          ],
          [
            1678119783,
            "209547264"
          ],
          [
            1678119903,
            "236421120"
          ],
          [
            1678120023,
            "246398976"
          ],
          [
            1678120143,
            "234692608"
          ],
          [
            1678120263,
            "242630656"
          ],
          [
            1678120383,
            "178106368"
          ],
          [
            1678120503,
            "241909760"
          ],
          [
            1678120623,
            "237105152"
          ],
          [
            1678120743,
            "188497920"
          ],
          [
            1678120863,
            "243748864"
          ],
          [
            1678120983,
            "241864704"
          ],
          [
            1678121103,
            "182534144"
          ],
          [
            1678121223,
            "266817536"
          ],
          [
            1678121343,
            "303693824"
          ],
          [
            1678121463,
            "245538816"
          ],
          [
            1678121583,
            "280055808"
          ],
          [
            1678121703,
            "251592704"
          ],
          [
            1678121823,
            "203710464"
          ],
          [
            1678121943,
            "279212032"
          ],
          [
            1678122063,
            "256319488"
          ],
          [
            1678122183,
            "195952640"
          ],
          [
            1678122303,
            "216363008"
          ],
          [
            1678122423,
            "200404992"
          ],
          [
            1678122543,
            "207376384"
          ],
          [
            1678122663,
            "196579328"
          ],
          [
            1678122783,
            "184737792"
          ],
          [
            1678122903,
            "266711040"
          ],
          [
            1678123023,
            "266522624"
          ],
          [
            1678123143,
            "228491264"
          ],
          [
            1678123263,
            "263725056"
          ],
          [
            1678123383,
            "239050752"
          ],
          [
            1678123503,
            "226304000"
          ],
          [
            1678123623,
            "261906432"
          ],
          [
            1678123743,
            "261369856"
          ],
          [
            1678123863,
            "208195584"
          ],
          [
            1678123983,
            "266063872"
          ],
          [
            1678124103,
            "246579200"
          ],
          [
            1678124223,
            "221057024"
          ],
          [
            1678124343,
            "267919360"
          ],
          [
            1678124463,
            "243396608"
          ],
          [
            1678124583,
            "261976064"
          ],
          [
            1678124703,
            "253431808"
          ]
        ]
      }
    ]
  }
}