{
  "status": "success",
  "data": {
    "resultType": "matrix",
    "result": [
      {
        "metric": {
          "host_id": "343177628"
        },
        "values": [
          [
            1679483021,
            "0"
          ],
          [
            1679483222,
            "0.13"
          ],
          [
            1679483423,
            "0.02"
          ],
          [
            1679483624,
            "0.07"
          ],
          [
            1679483825,
            "0.66"
          ],
          [
            1679484026,
            "0.6"
          ],
          [
            1679484227,
            "0.01"
          ],
          [
            1679484428,
            "0.01"
          ],
          [
            1679484629,
            "0.24"
          ],
          [
            1679484830,
            "0.99"
          ],
          [
            1679485031,
            "0.02"
          ],
          [
            1679485232,
            "0"
          ],
          [
            1679485433,
            "0.82"
          ],
          [
            1679485634,
            "0.1"
          ],
          [
            1679485835,
            "0.01"
          ],
          [
            1679486036,
            "0"
          ],
          [
            1679486237,
            "0.02"
          ],
          [
            1679486438,
            "0"
          ],
          [
            1679486639,
            "0"
          ],
          [
            1679486840,
            "0.04"
          ],
          [
            1679487041,
            "0"
          ],
          [
            1679487242,
            "0"
          ],
          [
            1679487443,
            "0.44"
          ],
          [
            1679487644,
            "0.06"
          ],
          [
            1679487845,
            "0"
          ],
          [
            1679488046,
            "1.09"
          ],
          [
            1679488247,
            "0.72"
          ],
          [
            1679488448,
            "0.7"
          ],
          [
            1679488649,
            "0.57"
          ],
          [
            1679488850,
            "0.47"
          ],
          [
            1679489051,
            "0.06"
          ],
          [
            1679489252,
            "0"
          ],
          [
            1679489453,
            "0.49"
          ],
          [
            1679489654,
            "0.06"
          ],
          [
            1679489855,
            "0"
          ],
          [
            1679490056,
            "1.06"
          ],
          [
            1679490257,
            "0.81"
          ],
          [
            1679490458,
            "0.89"
          ],
          [
            1679490659,
            "0.1"
          ],
          [
            1679490860,
            "0.01"
          ],
          [
            1679491061,
            "0"
          ],
          [
            1679491262,
            "1.37"
          ],
          [
            1679491463,
            "1.15"
          ],
          [
            1679491664,
            "0.57"
          ],
          [
            1679491865,
            "0.01"
          ],
          [
            1679492066,
            "0"
          ],
          [
            1679492267,
            "1.54"
          ],
          [
            1679492468,
            "2.7"
          ],
          [
            1679492669,
            "2.94"
          ],
          [
            1679492870,
            "1.96"
          ],
          [
            1679493071,
            "0.25"
          ],
          [
            1679493272,
            "0.03"
          ],
          [
            1679493473,
            "0"
          ],
          [
            1679493674,
            "0.27"
          ],
          [
            1679493875,
            "0.03"
          ],
          [
            1679494076,
            "0"
          ],
          [
            1679494277,
            "2.26"
          ],
          [
            1679494478,
            "2.69"
          ],
          [
            1679494679,
            "0.16"
          ],
          [
            1679494880,
            "0"
          ],
          [
            1679495081,
            "0.24"
          ],
          [
            1679495282,
            "0.12"
          ],
          [
            1679495483,
            "0"
          ],
          [
            1679495684,
            "0.6"
          ],
          [
            1679495885,
            "0.57"
          ],
          [
            1679496086,
            "0.12"
          ],
          [
            1679496287,
            "0.07"
          ],
          [
            1679496488,
            "0.5"
          ],
          [
            1679496689,
            "0.01"
          ],
          [
            1679496890,
            "1.15"
          ],
          [
            1679497091,
            "0.28"
          ],
          [
            1679497292,
            "0"
          ],
          [
            1679497493,
            "1.41"
          ],
          [
            1679497694,
            "0.29"
          ],
          [
            1679497895,
            "0"
          ],
          [
            1679498096,
            "2.8"
          ],
          [
            1679498297,
            "0.41"
          ],
          [
            1679498498,
            "0"
          ],
          [
            1679498699,
            "1.41"
          ],
          [
            1679498900,
            "2.13"
          ],
          [
            1679499101,
            "0.1"
          ],
          [
            1679499302,
            "0"
          ],
          [
            1679499503,
            "1.78"
          ],
          [
            1679499704,
            "0.25"
          ],
          [
            1679499905,
            "0"
          ],
          [
            1679500106,
            "0"
          ],
          [
            1679500307,
            "0.88"
          ],
          [
            1679500508,
            "0.01"
          ],
          [
            1679500709,
            "0"
          ],
          [
            1679500910,
            "1.83"
          ],
          [
            1679501111,
            "0.51"
          ],
          [
            1679501312,
            "0.07"
          ],
          [
            1679501513,
            "0"
          ],
          [
            1679501714,
            "1.83"
          ],
          [
            1679501915,
            "0.88"
          ],
          [
            1679502116,
            "1.38"
          ],
          [
            1679502317,
            "0.08"
          ],
          [
            1679502518,
            "0.01"
          ],
          [
            1679502719,
            "0"
          ],
          [
            1679502920,
            "0.06"
          ],
          [
            1679503121,
            "0"
          ],
          [
            1679503322,
            "0"
          ],
          [
            1679503523,
            "0.16"
          ],
          [
            1679503724,
            "0.02"
          ],
          [
            1679503925,
            "0"
          ],
          [
            1679504126,
            "2.24"
          ],
          [
            1679504327,
            "2.66"
          ],
          [
            1679504528,
            "0.19"
          ],
          [
            1679504729,
            "0"
          ],
          [
            1679504930,
            "1.08"
          ],
          [
            1679505131,
            "0.78"
          ],
          [
            1679505332,
            "0.01"
          ],
          [
            1679505533,
            "0"
          ],
          [
            1679505734,
            "1.11"
          ],
          [
            1679505935,
            "0.05"
          ],
          [
            1679506136,
            "0"
          ],
          [
            1679506337,
            "0.24"
          ],
          [
            1679506538,
            "2.08"
          ],
          [
            1679506739,
            "0.56"
          ],
          [
            1679506940,
            "0.07"
          ],
          [
            1679507141,
            "0"
          ],
          [
            1679507342,
            "0.92"
          ],
          [
            1679507543,
            "0.22"
          ],
          [
            1679507744,
            "0.05"
          ],
          [
            1679507945,
            "0.13"
          ],
          [
            1679508146,
            "1.37"
          ],
          [
            1679508347,
            "0.03"
          ],
          [
            1679508548,
            "0.01"
          ],
          [
            1679508749,
            "1.49"
          ],
          [
            1679508950,
            "0.6"
          ],
          [
            1679509151,
            "0.03"
          ],
          [
            1679509352,
            "0"
          ],
          [
            1679509553,
            "0.72"
          ],
          [
            1679509754,
            "0.04"
          ],
          [
            1679509955,
            "0"
          ],
          [
            1679510156,
            "0.06"
          ],
          [
            1679510357,
            "0.15"
          ],
          [
            1679510558,
            "0.02"
          ],
          [
            1679510759,
            "0"
          ],
          [
            1679510960,
            "0.28"
          ],
          [
            1679511161,
            "0.04"
          ],
          [
            1679511362,
            "0"
          ],
          [
            1679511563,
            "1.6"
          ],
          [
            1679511764,
            "0.21"
          ],
          [
            1679511965,
            "0"
          ],
          [
            1679512166,
            "0.24"
          ],
          [
            1679512367,
            "0.03"
          ],
          [
            1679512568,
            "0"
          ],
          [
            1679512769,
            "0.51"
          ],
          [
            1679512970,
            "0.11"
          ],
          [
            1679513171,
            "0.01"
          ],
          [
            1679513372,
            "0"
          ],
          [
            1679513573,
            "0.08"
          ],
          [
            1679513774,
            "0.01"
          ],
          [
            1679513975,
            "0"
          ],
          [
            1679514176,
            "0.44"
          ],
          [
            1679514377,
            "0.06"
          ],
          [
            1679514578,
            "0"
          ],
          [
            1679514779,
            "0.66"
          ],
          [
            1679514980,
            "1.77"
          ],
          [
            1679515181,
            "0.03"
          ],
          [
            1679515382,
            "0"
          ],
          [
            1679515583,
            "0.28"
          ],
          [
            1679515784,
            "0"
          ],
          [
            1679515985,
            "0"
          ],
          [
            1679516186,
            "2.31"
          ],
          [
            1679516387,
            "0.04"
          ],
          [
            1679516588,
            "0"
          ],
          [
            1679516789,
            "1.02"
          ],
          [
            1679516990,
            "0.02"
          ],
          [
            1679517191,
            "0"
          ],
          [
            1679517392,
            "0.9"
          ],
          [
            1679517593,
            "1.72"
          ],
          [
            1679517794,
            "5.23"
          ],
          [
            1679517995,
            "0.7"
          ],
          [
            1679518196,
            "0.01"
          ],
          [
            1679518397,
            "4.33"
          ],
          [
            1679518598,
            "5"
          ],
          [
            1679518799,
            "6.97"
          ],
          [
            1679519000,
            "6.74"
          ],
          [
            1679519201,
            "8.26"
          ],
          [
            1679519402,
            "5.26"
          ],
          [
            1679519603,
            "0.26"
          ],
          [
            1679519804,
            "0.03"
          ],
          [
            1679520005,
            "3.44"
          ],
          [
            1679520206,
            "1.01"
          ],
          [
            1679520407,
            "0.13"
          ],
          [
            1679520608,
            "0"
          ],
          [
            1679520809,
            "4.99"
          ],
          [
            1679521010,
            "0.09"
          ],
          [
            1679521211,
            "0.01"
          ],
          [
            1679521412,
            "5.01"
          ],
          [
            1679521613,
            "0.1"
          ],
          [
            1679521814,
            "0.01"
          ],
          [
            1679522015,
            "4.44"
          ],
          [
            1679522216,
            "2.02"
          ],
          [
            1679522417,
            "0.27"
          ],
          [
            1679522618,
            "0"
          ],
          [
            1679522819,
            "2.02"
          ],
          [
            1679523020,
            "0.27"
          ],
          [
            1679523221,
            "0"
          ],
          [
            1679523422,
            "2.26"
          ],
          [
            1679523623,
            "0.3"
          ],
          [
            1679523824,
            "0"
          ],
          [
            1679524025,
            "2.07"
          ],
          [
            1679524226,
            "0.28"
          ],
          [
            1679524427,
            "0"
          ],
          [
            1679524628,
            "2.25"
          ],
          [
            1679524829,
            "0.3"
          ],
          [
            1679525030,
            "0"
          ],
          [
            1679525231,
            "1.75"
          ],
          [
            1679525432,
            "0.23"
          ],
          [
            1679525633,
            "0"
          ],
          [
            1679525834,
            "5.83"
          ],
          [
            1679526035,
            "6.45"
          ],
          [
            1679526236,
            "0.11"
          ],
          [
            1679526437,
            "0"
          ],
          [
            1679526638,
            "2.92"
          ],
          [
            1679526839,
            "6.05"
          ],
          [
            1679527040,
            "0.18"
          ],
          [
            1679527241,
            "0.02"
          ],
          [
            1679527442,
            "2.43"
          ],
          [
            1679527643,
            "1.35"
          ],
          [
            1679527844,
            "0.18"
          ],
          [
            1679528045,
            "0"
          ],
          [
            1679528246,
            "5.15"
          ],
          [
            1679528447,
            "4.01"
          ],
          [
            1679528648,
            "0.07"
          ],
          [
            1679528849,
            "0"
          ],
          [
            1679529050,
            "0.37"
          ],
          [
            1679529251,
            "0.05"
          ],
          [
            1679529452,
            "0.04"
          ],
          [
            1679529653,
            "3.7"
          ],
          [
            1679529854,
            "3.42"
          ],
          [
            1679530055,
            "0.06"
          ],
          [
            1679530256,
            "0"
          ],
          [
            1679530457,
            "3.31"
          ],
          [
            1679530658,
            "2.29"
          ],
          [
            1679530859,
            "0.45"
          ],
          [
            1679531060,
            "0.06"
          ],
          [
            1679531261,
            "0"
          ],
          [
            1679531462,
            "2.03"
          ],
          [
            1679531663,
            "0.27"
          ],
          [
            1679531864,
            "0"
          ],
          [
            1679532065,
            "2.51"
          ],
          [
            1679532266,
            "2.17"
          ],
          [
            1679532467,
            "4.3"
          ],
          [
            1679532668,
            "0.35"
          ],
          [
            1679532869,
            "0.04"
          ],
          [
            1679533070,
            "0"
          ],
          [
            1679533271,
            "2.55"
          ],
          [
            1679533472,
            "0.68"
          ],
          [
            1679533673,
            "0.01"
          ],
          [
            1679533874,
            "1.43"
          ],
          [
            1679534075,
            "3.48"
          ],
          [
            1679534276,
            "0.31"
          ],
          [
            1679534477,
            "0"
          ],
          [
            1679534678,
            "0"
          ],
          [
            1679534879,
            "1.95"
          ],
          [
            1679535080,
            "0.04"
          ],
          [
            1679535281,
            "0"
          ],
          [
            1679535482,
            "1.67"
          ],
          [
            1679535683,
            "0.03"
          ],
          [
            1679535884,
            "0"
          ],
          [
            1679536085,
            "1.36"
          ],
          [
            1679536286,
            "0.7"
          ],
          [
            1679536487,
            "0.09"
          ],
          [
            1679536688,
            "0"
          ],
          [
            1679536889,
            "0.28"
          ],
          [
            1679537090,
            "0.04"
          ],
          [
            1679537291,
            "0"
          ],
          [
            1679537492,
            "3.35"
          ],
          [
            1679537693,
            "0.06"
          ],
          [
            1679537894,
            "0"
          ],
          [
            1679538095,
            "3.18"
          ],
          [
            1679538296,
            "0.06"
          ],
          [
            1679538497,
            "0"
          ],
          [
            1679538698,
            "2.32"
          ],
          [
            1679538899,
            "0.04"
          ],
          [
            1679539100,
            "0.04"
          ],
          [
            1679539301,
            "2.4"
          ],
          [
            1679539502,
            "0.3"
          ],
          [
            1679539703,
            "0.04"
          ],
          [
            1679539904,
            "0.04"
          ],
          [
            1679540105,
            "2.4"
          ],
          [
            1679540306,
            "0.65"
          ],
          [
            1679540507,
            "0.01"
          ],
          [
            1679540708,
            "0.62"
          ],
          [
            1679540909,
            "3.79"
          ],
          [
            1679541110,
            "1.15"
          ],
          [
            1679541311,
            "0.02"
          ],
          [
            1679541512,
            "0.07"
          ],
          [
            1679541713,
            "2.87"
          ],
          [
            1679541914,
            "2.96"
          ],
          [
            1679542115,
            "1.53"
          ],
          [
            1679542316,
            "0.46"
          ],
          [
            1679542517,
            "0.01"
          ],
          [
            1679542718,
            "0"
          ],
          [
            1679542919,
            "0.72"
          ],
          [
            1679543120,
            "0.01"
          ],
          [
            1679543321,
            "0"
          ],
          [
            1679543522,
            "2.05"
          ],
          [
            1679543723,
            "0.21"
          ],
          [
            1679543924,
            "0.03"
          ],
          [
            1679544125,
            "0"
          ],
          [
            1679544326,
            "1.98"
          ],
          [
            1679544527,
            "2.91"
          ],
          [
            1679544728,
            "0.1"
          ],
          [
            1679544929,
            "0"
          ],
          [
            1679545130,
            "1.44"
          ],
          [
            1679545331,
            "0.05"
          ],
          [
            1679545532,
            "0"
          ],
          [
            1679545733,
            "3.29"
          ],
          [
            1679545934,
            "0.44"
          ],
          [
            1679546135,
            "0"
          ],
          [
            1679546336,
            "1.79"
          ],
          [
            1679546537,
            "1.78"
          ],
          [
            1679546738,
            "0.13"
          ],
          [
            1679546939,
            "0"
          ],
          [
            1679547140,
            "0"
          ],
          [
            1679547341,
            "0.43"
          ],
          [
            1679547542,
            "0"
          ],
          [
            1679547743,
            "0"
          ],
          [
            1679547944,
            "0.43"
          ],
          [
            1679548145,
            "0"
          ],
          [
            1679548346,
            "0"
          ],
          [
            1679548547,
            "0.92"
          ],
          [
            1679548748,
            "0.03"
          ],
          [
            1679548949,
            "0"
          ],
          [
            1679549150,
            "0.61"
          ],
          [
            1679549351,
            "0.01"
          ],
          [
            1679549552,
            "0"
          ],
          [
            1679549753,
            "0.48"
          ],
          [
            1679549954,
            "0.01"
          ],
          [
            1679550155,
            "0.02"
          ],
          [
            1679550356,
            "2.25"
          ],
          [
            1679550557,
            "1.06"
          ],
          [
            1679550758,
            "1.57"
          ],
          [
            1679550959,
            "0.35"
          ],
          [
            1679551160,
            "0"
          ],
          [
            1679551361,
            "0"
          ],
          [
            1679551562,
            "1.1"
          ],
          [
            1679551763,
            "0.07"
          ],
          [
            1679551964,
            "0.01"
          ],
          [
            1679552165,
            "0"
          ],
          [
            1679552366,
            "0.1"
          ],
          [
            1679552567,
            "0.01"
          ],
          [
            1679552768,
            "0"
          ],
          [
            1679552969,
            "1.97"
          ],
          [
            1679553170,
            "0.32"
          ],
          [
            1679553371,
            "0.01"
          ],
          [
            1679553572,
            "2.35"
          ],
          [
            1679553773,
            "0.67"
          ],
          [
            1679553974,
            "0.09"
          ],
          [
            1679554175,
            "0"
          ],
          [
            1679554376,
            "2.06"
          ],
          [
            1679554577,
            "1.39"
          ],
          [
            1679554778,
            "0.05"
          ],
          [
            1679554979,
            "0"
          ],
          [
            1679555180,
            "1.82"
          ],
          [
            1679555381,
            "0.94"
          ],
          [
            1679555582,
            "0.01"
          ],
          [
            1679555783,
            "0"
          ],
          [
            1679555984,
            "1.01"
          ],
          [
            1679556185,
            "3.62"
          ],
          [
            1679556386,
            "2.06"
          ],
          [
            1679556587,
            "0.03"
          ],
          [
            1679556788,
            "0"
          ],
          [
            1679556989,
            "0.44"
          ],
          [
            1679557190,
            "0"
          ],
          [
            1679557391,
            "0"
          ],
          [
            1679557592,
            "1.06"
          ],
          [
            1679557793,
            "0.16"
          ],
          [
            1679557994,
            "0"
          ],
          [
            1679558195,
            "0"
          ],
          [
            1679558396,
            "1.99"
          ],
          [
            1679558597,
            "0.35"
          ],
          [
            1679558798,
            "0.04"
          ],
          [
            1679558999,
            "0"
          ],
          [
            1679559200,
            "2.19"
          ],
          [
            1679559401,
            "0.29"
          ],
          [
            1679559602,
            "0"
          ],
          [
            1679559803,
            "1.06"
          ],
          [
            1679560004,
            "0.14"
          ],
          [
            1679560205,
            "0"
          ],
          [
            1679560406,
            "1.87"
          ],
          [
            1679560607,
            "1.08"
          ],
          [
            1679560808,
            "0.02"
          ],
          [
            1679561009,
            "0.16"
          ],
          [
            1679561210,
            "0.44"
          ],
          [
            1679561411,
            "0"
          ],
          [
            1679561612,
            "0.1"
          ],
          [
            1679561813,
            "0.13"
          ],
          [
            1679562014,
            "0.02"
          ],
          [
            1679562215,
            "0.01"
          ],
          [
            1679562416,
            "3.03"
          ],
          [
            1679562617,
            "2.13"
          ],
          [
            1679562818,
            "0.14"
          ],
          [
            1679563019,
            "0"
          ],
          [
            1679563220,
            "0"
          ],
          [
            1679563421,
            "3.47"
          ]
        ]
      }
    ]
  }
}